<?xml version="1.0"?>
<PhysEngMaterialDB>
  
  <IsotropicMaterial>
    <Name>Al EN AW7075</Name>
    <Title>Aluminium EN AW7075</Title>
    <Category>Alloy</Category>
    <Properties>
      <Density Value="1175" Unit="kg/m^3"/>
      <ThermalConductivity T="20" Tunit="°C" Value="145" Unit="W/(m*K)"/>
    </Properties>
  </IsotropicMaterial>

  <IsotropicMaterial>
    <Name>Al EN AW5083</Name>
    <Title>Aluminium EN AW5083</Title>
    <Category>Alloy</Category>
    <Properties>
      <Density Value="1175" Unit="kg/m^3"/>
      <ThermalConductivity T="20" Tunit="°C" Value="125" Unit="W/(m*K)"/>
    </Properties>
  </IsotropicMaterial>

  <IsotropicMaterial>
    <Name>Al EN AW6082</Name>
    <Title>Aluminium EN AW6082</Title>
    <Category>Alloy</Category>
    <Properties>
      <Density Value="1175" Unit="kg/m^3"/>
      <ThermalConductivity T="20" Tunit="°C" Value="195" Unit="W/(m*K)"/>
    </Properties>
  </IsotropicMaterial>

  <IsotropicMaterial>
    <Name>Al EN AW5754</Name>
    <Title>Aluminium EN AW5754</Title>
    <Category>Alloy</Category>
    <Properties>
      <Density Value="1175" Unit="kg/m^3"/>
      <ThermalConductivity T="20" Tunit="°C" Value="150" Unit="W/(m*K)"/>
    </Properties>
  </IsotropicMaterial>

  <IsotropicMaterial>
    <Name>Cu EN CW004A</Name>
    <Title>Copper EN CW004A</Title>
    <Category>Alloy</Category>
    <Properties>
      <Density Value="8.93" Unit="g/cm^3"/>
      <ThermalConductivity T="20" Tunit="°C" Value="394" Unit="W/(m*K)"/>
    </Properties>
  </IsotropicMaterial>

  <IsotropicMaterial>
    <Name>Brass EN CW614N</Name>
    <Title>Brass EN CW614N</Title>
    <Category>Alloy</Category>
    <Properties>
      <Density Value="8.47" Unit="g/cm^3"/>
      <ThermalConductivity>
        <Value T="20" Tunit="°C" Value="123" Unit="W/(m*K)"/>
        <Value T="-200" Tunit="°C" Value="50" Unit="W/(m*K)"/>
      </ThermalConductivity>
    </Properties>
  </IsotropicMaterial>
  
</PhysEngMaterialDB>
