{
  "descriptionHash": "A022B12680D160FE614F2D4A89CBB0218C79875E48322DA65839F316B2FAFE7F4E7D47C01D83185E6BAC700687410D3DBB790B983E6F6E020DBFBEDD6643B1E5",
  "descriptionLocation": "../../openapi.json",
  "lockFileVersion": "1.0.0",
  "kiotaVersion": "1.21.0",
  "clientClassName": "RegistryClient",
  "typeAccessModifier": "Public",
  "clientNamespaceName": "client",
  "language": "Python",
  "usesBackingStore": false,
  "excludeBackwardCompatible": false,
  "includeAdditionalData": true,
  "disableSSLValidation": false,
  "serializers": [
    "Microsoft.Kiota.Serialization.Json.JsonSerializationWriterFactory",
    "Microsoft.Kiota.Serialization.Text.TextSerializationWriterFactory",
    "Microsoft.Kiota.Serialization.Form.FormSerializationWriterFactory",
    "Microsoft.Kiota.Serialization.Multipart.MultipartSerializationWriterFactory"
  ],
  "deserializers": [
    "Microsoft.Kiota.Serialization.Json.JsonParseNodeFactory",
    "Microsoft.Kiota.Serialization.Text.TextParseNodeFactory",
    "Microsoft.Kiota.Serialization.Form.FormParseNodeFactory"
  ],
  "structuredMimeTypes": [
    "application/json",
    "text/plain;q=0.9",
    "application/x-www-form-urlencoded;q=0.2",
    "multipart/form-data;q=0.1"
  ],
  "includePatterns": [],
  "excludePatterns": [],
  "disabledValidationRules": []
}